{
  "$schema": "https://context7.com/schema/context7.json",
  "version": "1.0.0",
  "projectTitle": "X-Plane 12 SDK",
  "description": "Complete X-Plane 12 SDK documentation including XPLM APIs, Widget system, and development guides",
  "folders": [
    "docs"
  ],
  "excludeFolders": [
    "raw_data",
    "scripts",
    "__pycache__",
    ".git",
    "node_modules",
    "build",
    "dist"
  ],
  "excludeFiles": [
    "package.json",
    "tsconfig.json",
    ".gitignore",
    ".DS_Store",
    "Thumbs.db",
    "requirements.txt",
    "integration_test_report.json",
    "validation_report.json"
  ],
  "rules": [
    "Use XPLM prefix for all X-Plane API functions",
    "Include proper error handling for all API calls",
    "Reference official X-Plane documentation for latest updates",
    "Use appropriate data types as defined in XPLM headers",
    "Follow X-Plane SDK naming conventions for plugins",
    "Include function signatures with parameter descriptions",
    "Provide code examples for complex API usage",
    "Document callback function requirements and signatures",
    "Include version compatibility information for API functions",
    "Reference related API functions in cross-references",
    "Use proper C/C++ syntax in code examples",
    "Include error codes and their meanings",
    "Document thread safety considerations for API calls",
    "Provide performance considerations for resource-intensive operations",
    "Include platform-specific implementation notes where applicable"
  ]
}